polycubetools/__init__.py
polycubetools/errors.py
polycubetools/grid.py
polycubetools/hull.py
polycubetools/models.py
polycubetools/py.typed
polycubetools/solver.py
polycubetools/utils.py
polycubetools/data/heptacubes.json
polycubetools/data/hexacubes.json
polycubetools/data/pentacubes.json
polycubetools-1.1.1.dist-info/licenses/LICENSE
polycubetools-1.1.1.dist-info/METADATA
polycubetools-1.1.1.dist-info/WHEEL
polycubetools-1.1.1.dist-info/top_level.txt
polycubetools-1.1.1.dist-info/RECORD
